apexomni_x86_mac-3.2.0.data/data/apexpro/libzklink_sdk.dylib
apexomni_x86_mac-3.2.0.data/data/apexpro/pedersen_params.json
apexomni_x86_mac-3.2.0.dist-info/licenses/LICENSE
apexpro/__init__.py
apexpro/_websocket_stream.py
apexpro/constants.py
apexpro/errors.py
apexpro/eth.py
apexpro/exceptions.py
apexpro/http_private.py
apexpro/http_private_sign.py
apexpro/http_private_stark_key_sign.py
apexpro/http_private_v3.py
apexpro/http_public.py
apexpro/libzklink_sdk-arm.dylib
apexpro/libzklink_sdk-x86.dylib
apexpro/libzklink_sdk.dylib
apexpro/libzklink_sdk.so
apexpro/models.py
apexpro/websocket_api.py
apexpro/zklink_sdk-arm.py
apexpro/zklink_sdk-pc.py
apexpro/zklink_sdk-x86.py
apexpro/zklink_sdk.dll
apexpro/zklink_sdk.py
apexpro/abi/erc20.json
apexpro/abi/starkware-perpetuals.json
apexpro/eth_signing/__init__.py
apexpro/eth_signing/eth_prive_action.py
apexpro/eth_signing/onboarding_action.py
apexpro/eth_signing/sign_off_chain_action.py
apexpro/eth_signing/signers.py
apexpro/eth_signing/util.py
apexpro/helpers/__init__.py
apexpro/helpers/db.py
apexpro/helpers/request_helpers.py
apexpro/helpers/requests.py
apexpro/helpers/util.py
apexpro/starkex/__init__.py
apexpro/starkex/conditional_transfer.py
apexpro/starkex/constants.py
apexpro/starkex/helpers.py
apexpro/starkex/order.py
apexpro/starkex/signable.py
apexpro/starkex/transfer.py
apexpro/starkex/withdrawal.py
apexpro/starkex/starkex_resources/__init__.py
apexpro/starkex/starkex_resources/cpp_signature.py
apexpro/starkex/starkex_resources/math_utils.py
apexpro/starkex/starkex_resources/pedersen_params.json
apexpro/starkex/starkex_resources/proxy.py
apexpro/starkex/starkex_resources/python_signature.py
tests/__init__.py
tests/account_value.py
tests/account_value_ws.py
tests/constants.py
tests/demo_create_order_v3.py
tests/demo_deposit.py
tests/demo_private.py
tests/demo_private_apikeys_v3.py
tests/demo_private_v2.py
tests/demo_private_v3.py
tests/demo_public.py
tests/demo_public_v2.py
tests/demo_public_v3.py
tests/demo_register.py
tests/demo_register_mul_address.py
apexomni_x86_mac-3.2.0.dist-info/METADATA
apexomni_x86_mac-3.2.0.dist-info/WHEEL
apexomni_x86_mac-3.2.0.dist-info/top_level.txt
apexomni_x86_mac-3.2.0.dist-info/RECORD
